get_version/__init__.py
get_version/__main__.py
get_version/versions.py
get_the_version-0.1.5.dist-info/LICENSE
get_the_version-0.1.5.dist-info/METADATA
get_the_version-0.1.5.dist-info/WHEEL
get_the_version-0.1.5.dist-info/entry_points.txt
get_the_version-0.1.5.dist-info/top_level.txt
get_the_version-0.1.5.dist-info/RECORD
