Metadata-Version: 2.1
Name: get-the-version
Version: 0.1.5
Summary: Get the version of so many things.
Home-page: https://github.com/duyixian1234/get_version
Author: Yixian Du
Author-email: duyixian1234@qq.com
License: MIT
Platform: UNKNOWN
Classifier: License :: OSI Approved :: MIT License
Classifier: Programming Language :: Python
Classifier: Programming Language :: Python :: 3.7
Classifier: Programming Language :: Python :: Implementation :: CPython
Requires-Dist: click
